myfunctions_khikmatillo1/__init__.py
myfunctions_khikmatillo1/math.py
myfunctions_khikmatillo1-0.0.10.dist-info/METADATA
myfunctions_khikmatillo1-0.0.10.dist-info/WHEEL
myfunctions_khikmatillo1-0.0.10.dist-info/top_level.txt
myfunctions_khikmatillo1-0.0.10.dist-info/RECORD
