Metadata-Version: 2.1
Name: myfunctions-khikmatillo1
Version: 0.0.10
Summary: A description of your package
Home-page: https://github.com/khikmatillo1/
Author: Hikmatillo Lutfullaev
Author-email: twaravancargo@gmail.com
License: MIT
Platform: UNKNOWN
Classifier: Programming Language :: Python :: 3
Classifier: License :: OSI Approved :: MIT License
Classifier: Operating System :: OS Independent
Requires-Python: >=3.6
